sc2replaylib
