Metadata-Version: 1.0
Name: sc2replay-lib
Version: 0.1.2
Summary: Basic library for reading details about a Blizzard (TM) StarCraft(TM) 2 replay file
Home-page: https://github.com/dcbarans/sc2replay-lib
Author: Dominic Baranski
Author-email: dominic.baranski@gmail.com
License: MPL 1.1
Keywords: starcraft,sc,starcraft 2,sc2,parser,replay
Platform: UNKNOWN
Classifier: Environment :: Console
Classifier: Development Status :: 4 - Beta
Classifier: Programming Language :: Python
Classifier: Programming Language :: Python :: 2.7
Classifier: Intended Audience :: Developers
Classifier: License :: OSI Approved :: Mozilla Public License 1.1 (MPL 1.1)
Classifier: Natural Language :: English
Classifier: Operating System :: OS Independent
Classifier: Environment :: Other Environment
Classifier: Topic :: Utilities
Classifier: Topic :: Software Development :: Libraries
Classifier: Topic :: Games/Entertainment :: Real Time Strategy
